odoo/addons/only_name_on_sale_order_line_description/README.rst
odoo/addons/only_name_on_sale_order_line_description/__init__.py
odoo/addons/only_name_on_sale_order_line_description/__manifest__.py
odoo/addons/only_name_on_sale_order_line_description/__pycache__/__init__.cpython-38.pyc
odoo/addons/only_name_on_sale_order_line_description/i18n/es.po
odoo/addons/only_name_on_sale_order_line_description/i18n/sale_order_line_description.pot
odoo/addons/only_name_on_sale_order_line_description/models/__init__.py
odoo/addons/only_name_on_sale_order_line_description/models/res_config_settings.py
odoo/addons/only_name_on_sale_order_line_description/models/sale_order_line.py
odoo/addons/only_name_on_sale_order_line_description/models/__pycache__/__init__.cpython-38.pyc
odoo/addons/only_name_on_sale_order_line_description/models/__pycache__/res_config_settings.cpython-38.pyc
odoo/addons/only_name_on_sale_order_line_description/models/__pycache__/sale_order_line.cpython-38.pyc
odoo/addons/only_name_on_sale_order_line_description/security/sale_security.xml
odoo/addons/only_name_on_sale_order_line_description/views/res_config_settings_views.xml
odoo14_addon_only_name_on_sale_order_line_description-14.0.0.0.1.dist-info/METADATA
odoo14_addon_only_name_on_sale_order_line_description-14.0.0.0.1.dist-info/WHEEL
odoo14_addon_only_name_on_sale_order_line_description-14.0.0.0.1.dist-info/top_level.txt
odoo14_addon_only_name_on_sale_order_line_description-14.0.0.0.1.dist-info/RECORD
