Metadata-Version: 2.1
Name: odoo14-addon-only-name-on-sale-order-line-description
Version: 14.0.0.0.1
Summary: Only Name on sale order line description
Home-page: https://talaios.coop
Author: Talaios
License: AGPL-3
Platform: UNKNOWN
Classifier: Programming Language :: Python
Classifier: Framework :: Odoo
Classifier: Framework :: Odoo :: 14.0
Classifier: License :: OSI Approved :: GNU Affero General Public License v3
Requires-Python: >=3.6
Requires-Dist: odoo <14.1dev,>=14.0a
